lyntin/__init__.py
lyntin/ansi.py
lyntin/argparser.py
lyntin/commandmanager.py
lyntin/config.py
lyntin/constants.py
lyntin/engine.py
lyntin/event.py
lyntin/exported.py
lyntin/helpmanager.py
lyntin/history.py
lyntin/manager.py
lyntin/net.py
lyntin/session.py
lyntin/utils.py
lyntin/modules/__init__.py
lyntin/modules/action.py
lyntin/modules/advanced.py
lyntin/modules/alias.py
lyntin/modules/deed.py
lyntin/modules/gag.py
lyntin/modules/highlight.py
lyntin/modules/logger.py
lyntin/modules/lyntincmds.py
lyntin/modules/manual.py
lyntin/modules/modutils.py
lyntin/modules/scheduler.py
lyntin/modules/speedwalk.py
lyntin/modules/substitute.py
lyntin/modules/tintincmds.py
lyntin/modules/variable.py
lyntin/modules/testsystem/__init__.py
lyntin/modules/testsystem/alias.benchmark
lyntin/modules/testsystem/alias.test
lyntin/modules/testsystem/config.benchmark
lyntin/modules/testsystem/config.test
lyntin/modules/testsystem/gag.benchmark
lyntin/modules/testsystem/gag.test
lyntin/modules/testsystem/speedwalk.benchmark
lyntin/modules/testsystem/speedwalk.test
lyntin/modules/testsystem/testmodule.py
lyntin/modules/testsystem/tintin.benchmark
lyntin/modules/testsystem/tintin.test
lyntin/modules/testsystem/variable.benchmark
lyntin/modules/testsystem/variable.test
lyntin/ui/__init__.py
lyntin/ui/base.py
lyntin/ui/cursesui.py
lyntin/ui/message.py
lyntin/ui/textui.py
lyntin/ui/tkui.py
scripts/resume_zone.txt
scripts/runlyntin.py
scripts/runlyntin.pyw
tools/README
tools/__init__.py
tools/connection.py
tools/lyntinunittest.py
tools/server_error.log
tools/testserver.py
tools/toolsutils.py
tools/unitprof.py
lyntinv-5.0.1.dist-info/METADATA
lyntinv-5.0.1.dist-info/WHEEL
lyntinv-5.0.1.dist-info/licenses/LICENSE
lyntinv-5.0.1.dist-info/RECORD
