Metadata-Version: 2.4
Name: lyntinv
Version: 5.0.1
Summary: A MUD client
Project-URL: Homepage, https://gitlab.little-beak.com
Author-email: Drexl Spivey <drexl@little-beak.com>
License:                     GNU GENERAL PUBLIC LICENSE
License-File: LICENSE
Keywords: client,mud
Classifier: Development Status :: 4 - Beta
Classifier: Intended Audience :: Developers
Classifier: Intended Audience :: End Users/Desktop
Classifier: License :: OSI Approved :: GNU General Public License v3 (GPLv3)
Classifier: Operating System :: OS Independent
Classifier: Programming Language :: Python :: 3.7
Classifier: Topic :: Games/Entertainment :: Multi-User Dungeons (MUD)
Requires-Python: >=3.7
